{"ts": "2026-06-10T12:54:04.350116+00:00", "platform_id": "netts", "platform_name": "NETTS", "url": "https://netts.io/", "chain": "TRON", "product_type": "energy_purchase", "minimum_order_energy": "N/A", "maximum_order_energy": "N/A", "platform_max_energy": "N/A", "65k_15m_price": "N/A", "65k_1h_price": 2.015, "65k_1d_price": "N/A", "65k_3d_price": "N/A", "65k_10d_price": "N/A", "130k_15m_price": "N/A", "130k_1h_price": 4.03, "130k_1d_price": "N/A", "130k_3d_price": "N/A", "130k_10d_price": "N/A"}
